README.md
ip_inspector/__init__.py
ip_inspector/cli.py
ip_inspector/config.py
ip_inspector/database.py
ip_inspector/etc/default.config.yaml
ip_inspector/inspector.py
ip_inspector/maxmind.py
ip_inspector/tor.py
ip_inspector-0.1.18.dist-info/METADATA
ip_inspector-0.1.18.dist-info/WHEEL
ip_inspector-0.1.18.dist-info/entry_points.txt
ip_inspector-0.1.18.dist-info/RECORD
